{"nombre":"Lucho","apellido":"Gonzalez","nickname":"Lucho","tusMeGusta":{"nombre":"Tus me Gusta","cancionesPlaylist":[{"id":11,"nombre":"Algo Magico","genero":"Reggaeton","rutaCancion":"audio/Rauw-Algo-Magico.wav","rutaPortada":"Media/AlgoMagicoPortada.png"},{"id":20,"nombre":"Diosa","genero":"Reggaeton","rutaCancion":"audio/Myke-Diosa.wav","rutaPortada":"Media/DiosaPortada.png"},{"id":16,"nombre":"Explicito","genero":"Reggaeton","rutaCancion":"audio/Myke-Explicito.wav","rutaPortada":"Media/ExplicitoPortada.png"}],"portada":"Media/MediaMG.png"},"fotoPortada":null,"contrasenia":"123","activo":true,"mail":"a@gmail.com"}
{"nombre":"Damian","apellido":"Lupo","nickname":"Lupo","tusMeGusta":{"nombre":"Tus me Gusta","cancionesPlaylist":[{"id":13,"nombre":"Besame Remix","genero":"Trap","rutaCancion":"audio/Besame-Remix.wav","rutaPortada":"Media/BesameRemixPortada.png"}],"portada":"Media/MediaMG.png"},"fotoPortada":null,"contrasenia":"123","activo":true,"mail":"lupencio42@gmail.com"}
